[
    {
        "raw_text": "🆕 NEW SIGNAL: FUNUSDT 🆕\n\n📊 Risk Analysis 📊\nVolume(24H) Ranked: 262th/468\nRisk Level: ⚠️ High\n\nEntry: 0.00348\n\n📝 Targets & Stop Loss\n----------------------------------------------\nLevel         Price       % Change from Entry\n----------------------------------------------\nTarget 1         0.00354      +1.72%\nTarget 2         0.00361      +3.74%\nTarget 3         0.00380      +9.20%\nTarget 4         0.00413      +18.68%\nStop Loss 1    0.00333      -4.31%\nStop Loss 2    0.00296      -14.94%\n----------------------------------------------\n\n🔍 Cek Sentimen Sosial Media untuk $FUN\n📊 Analisis Data Coinglass untuk FUN",
        "timestamp": "2025-06-06T06:40:03+00:00",
        "sender_id": 1218062484,
        "message_id": 4934,
        "coin_pair": "FUNUSDT",
        "risk_rank": "262th/468",
        "risk_level": "High",
        "entry_price": 0.00348,
        "targets": [
            {
                "level": 1,
                "price": 0.00354,
                "percentage_change": 1.72,
                "status": null
            },
            {
                "level": 2,
                "price": 0.00361,
                "percentage_change": 3.74,
                "status": null
            },
            {
                "level": 3,
                "price": 0.0038,
                "percentage_change": 9.2,
                "status": null
            },
            {
                "level": 4,
                "price": 0.00413,
                "percentage_change": 18.68,
                "status": null
            }
        ],
        "stop_losses": [
            {
                "level": 1,
                "price": 0.00333,
                "percentage_change": -4.31,
                "status": null
            },
            {
                "level": 2,
                "price": 0.00296,
                "percentage_change": -14.94,
                "status": null
            }
        ],
        "social_media_link": null,
        "data_analysis_link": null,
        "message_type": "NewSignal"
    },
    {
        "raw_text": "🆕 NEW SIGNAL: COMPUSDT 🆕\n\n📊 Risk Analysis 📊\nVolume(24H) Ranked: 89th/468\nRisk Level: 🟢 Normal\n\nEntry: 47.92\n\n📝 Targets & Stop Loss\n----------------------------------------------\nLevel         Price       % Change from Entry\n----------------------------------------------\nTarget 1         48.77      +1.77%\nTarget 2         49.62      +3.55%\nTarget 3         52.16      +8.85%\nTarget 4         56.40      +17.70%\nStop Loss 1    46.13      -3.74%\nStop Loss 2    41.13      -14.17%\n----------------------------------------------\n\n🔍 Cek Sentimen Sosial Media untuk $COMP\n📊 Analisis Data Coinglass untuk COMP",
        "timestamp": "2025-06-06T06:15:04+00:00",
        "sender_id": 1218062484,
        "message_id": 4932,
        "coin_pair": "COMPUSDT",
        "risk_rank": "89th/468",
        "risk_level": "Normal",
        "entry_price": 47.92,
        "targets": [
            {
                "level": 1,
                "price": 48.77,
                "percentage_change": 1.77,
                "status": null
            },
            {
                "level": 2,
                "price": 49.62,
                "percentage_change": 3.55,
                "status": null
            },
            {
                "level": 3,
                "price": 52.16,
                "percentage_change": 8.85,
                "status": null
            },
            {
                "level": 4,
                "price": 56.4,
                "percentage_change": 17.7,
                "status": null
            }
        ],
        "stop_losses": [
            {
                "level": 1,
                "price": 46.13,
                "percentage_change": -3.74,
                "status": null
            },
            {
                "level": 2,
                "price": 41.13,
                "percentage_change": -14.17,
                "status": null
            }
        ],
        "social_media_link": null,
        "data_analysis_link": null,
        "message_type": "NewSignal"
    },
    {
        "raw_text": "🆕 NEW SIGNAL: FARTCOINUSDT 🆕\n\n📊 Risk Analysis 📊\nVolume(24H) Ranked: 9th/468\nRisk Level: 🟢 Normal\n\nEntry: 0.9866\n\n📝 Targets & Stop Loss\n----------------------------------------------\nLevel         Price       % Change from Entry\n----------------------------------------------\nTarget 1         1.024      +3.79%\nTarget 2         1.061      +7.54%\nTarget 3         1.171      +18.69%\nTarget 4         1.356      +37.44%\nStop Loss 1    0.9014      -8.64%\nStop Loss 2    0.6909      -29.97%\n----------------------------------------------\n\n🔍 Cek Sentimen Sosial Media untuk $FARTCOIN\n📊 Analisis Data Coinglass untuk FARTCOIN",
        "timestamp": "2025-06-05T20:50:03+00:00",
        "sender_id": 1218062484,
        "message_id": 4917,
        "coin_pair": "FARTCOINUSDT",
        "risk_rank": "9th/468",
        "risk_level": "Normal",
        "entry_price": 0.9866,
        "targets": [
            {
                "level": 1,
                "price": 1.024,
                "percentage_change": 3.79,
                "status": null
            },
            {
                "level": 2,
                "price": 1.061,
                "percentage_change": 7.54,
                "status": null
            },
            {
                "level": 3,
                "price": 1.171,
                "percentage_change": 18.69,
                "status": null
            },
            {
                "level": 4,
                "price": 1.356,
                "percentage_change": 37.44,
                "status": null
            }
        ],
        "stop_losses": [
            {
                "level": 1,
                "price": 0.9014,
                "percentage_change": -8.64,
                "status": null
            },
            {
                "level": 2,
                "price": 0.6909,
                "percentage_change": -29.97,
                "status": null
            }
        ],
        "social_media_link": null,
        "data_analysis_link": null,
        "message_type": "NewSignal"
    },
    {
        "raw_text": "🆕 NEW SIGNAL: BTCDOMUSDT 🆕\n\n📊 Risk Analysis 📊\nVolume(24H) Ranked: 165th/468\nRisk Level: ⚠️ High\n\nEntry: 5226.90\n\n📝 Targets & Stop Loss\n----------------------------------------------\nLevel         Price       % Change from Entry\n----------------------------------------------\nTarget 1         5250.38      +0.45%\nTarget 2         5273.85      +0.90%\nTarget 3         5344.28      +2.25%\nTarget 4         5461.66      +4.49%\nStop Loss 1    5169.11      -1.11%\nStop Loss 2    5039.09      -3.59%\n----------------------------------------------\n\n🔍 Cek Sentimen Sosial Media untuk $BTCDOM\n📊 Analisis Data Coinglass untuk BTCDOM",
        "timestamp": "2025-06-05T19:20:03+00:00",
        "sender_id": 1218062484,
        "message_id": 4908,
        "coin_pair": "BTCDOMUSDT",
        "risk_rank": "165th/468",
        "risk_level": "High",
        "entry_price": 5226.9,
        "targets": [
            {
                "level": 1,
                "price": 5250.38,
                "percentage_change": 0.45,
                "status": null
            },
            {
                "level": 2,
                "price": 5273.85,
                "percentage_change": 0.9,
                "status": null
            },
            {
                "level": 3,
                "price": 5344.28,
                "percentage_change": 2.25,
                "status": null
            },
            {
                "level": 4,
                "price": 5461.66,
                "percentage_change": 4.49,
                "status": null
            }
        ],
        "stop_losses": [
            {
                "level": 1,
                "price": 5169.11,
                "percentage_change": -1.11,
                "status": null
            },
            {
                "level": 2,
                "price": 5039.09,
                "percentage_change": -3.59,
                "status": null
            }
        ],
        "social_media_link": null,
        "data_analysis_link": null,
        "message_type": "NewSignal"
    },
    {
        "raw_text": "🆕 NEW SIGNAL: 1000XUSDT 🆕\n\n📊 Risk Analysis 📊\nVolume(24H) Ranked: 392th/468\nRisk Level: ⚠️ High\n\nEntry: 0.0758\n\n📝 Targets & Stop Loss\n----------------------------------------------\nLevel         Price       % Change from Entry\n----------------------------------------------\nTarget 1         0.0768      +1.32%\nTarget 2         0.0779      +2.77%\nTarget 3         0.0809      +6.73%\nTarget 4         0.0859      +13.32%\nStop Loss 1    0.0734      -3.17%\nStop Loss 2    0.0678      -10.55%\n----------------------------------------------\n\n🔍 Cek Sentimen Sosial Media untuk $1000X\n📊 Analisis Data Coinglass untuk 1000X",
        "timestamp": "2025-06-05T16:05:03+00:00",
        "sender_id": 1218062484,
        "message_id": 4896,
        "coin_pair": "1000XUSDT",
        "risk_rank": "392th/468",
        "risk_level": "High",
        "entry_price": 0.0758,
        "targets": [
            {
                "level": 1,
                "price": 0.0768,
                "percentage_change": 1.32,
                "status": null
            },
            {
                "level": 2,
                "price": 0.0779,
                "percentage_change": 2.77,
                "status": null
            },
            {
                "level": 3,
                "price": 0.0809,
                "percentage_change": 6.73,
                "status": null
            },
            {
                "level": 4,
                "price": 0.0859,
                "percentage_change": 13.32,
                "status": null
            }
        ],
        "stop_losses": [
            {
                "level": 1,
                "price": 0.0734,
                "percentage_change": -3.17,
                "status": null
            },
            {
                "level": 2,
                "price": 0.0678,
                "percentage_change": -10.55,
                "status": null
            }
        ],
        "social_media_link": null,
        "data_analysis_link": null,
        "message_type": "NewSignal"
    }
]